Metadata-Version: 1.0
Name: my-gnb-distributions
Version: 1.5
Summary: Gaussian and Binomial distributions
Home-page: UNKNOWN
Author: Enerald Mclaniyi
Author-email: emclaniyi@gmail.com
License: UNKNOWN
Platform: UNKNOWN
